{
  "summary": "The phone call transcript reveals issues with the AI's ability to accurately capture and confirm user details, particularly the first name. Additionally, there are repetitive questions regarding text reminders that may confuse the caller. These issues could lead to a frustrating user experience.",
  "issues": [
    {
      "severity": "high",
      "category": "Data Accuracy",
      "evidence": "The AI incorrectly identifies the caller's first name as 'Metis' instead of 'Metish'.",
      "why_it_matters": "Incorrectly capturing user details can lead to miscommunication and potential privacy concerns.",
      "suggestion": "Implement better name recognition algorithms to ensure accurate capture of user names."
    },
    {
      "severity": "medium",
      "category": "User Experience",
      "evidence": "The AI repeatedly asks if the caller would like a text reminder for the appointment.",
      "why_it_matters": "Repetitive questioning can frustrate users and make the interaction feel less efficient.",
      "suggestion": "Streamline the conversation flow to avoid unnecessary repetition, especially for confirmation questions."
    }
  ],
  "overall_score": 5
}