{
  "summary": "The phone call transcript indicates a successful appointment booking process, but it also reveals a lack of engagement from the caller towards the end. The call ends abruptly without confirming if the caller wanted a text reminder, which could lead to confusion about the appointment details.",
  "issues": [
    {
      "severity": "med",
      "category": "User Engagement",
      "evidence": "The agent asks if the caller would like a text reminder, but the caller does not respond and the agent ends the call.",
      "why_it_matters": "Failing to confirm the text reminder could lead to the caller forgetting the appointment, impacting attendance rates.",
      "suggestion": "Implement a more engaging closing protocol that ensures the caller's needs are fully addressed before ending the call."
    },
    {
      "severity": "low",
      "category": "Clarity",
      "evidence": "The agent repeats the appointment details twice without confirming if the caller has any further questions.",
      "why_it_matters": "Repetition without engagement may lead to frustration or confusion for the caller, as they might feel their concerns are not being addressed.",
      "suggestion": "After confirming the appointment, ask if the caller has any additional questions or needs before concluding the call."
    }
  ],
  "overall_score": 7
}